client_server_chat_test/Client.py
client_server_chat_test/Server.py
client_server_chat_test/__init__.py
client_server_chat_test-2021.8.4.dist-info/METADATA
client_server_chat_test-2021.8.4.dist-info/WHEEL
client_server_chat_test-2021.8.4.dist-info/top_level.txt
client_server_chat_test-2021.8.4.dist-info/RECORD
